{
  "parent": "minecraft:block/block",
  "loader": "gtceu:machine",
  "machine": "phoenixcore:phoenix_cooling_component",
  "variants": {
    "active=false,hpca_part_damaged=false,is_formed=false": {
      "model": {
        "parent": "phoenixcore:block/phoenix_cooling_component_base",
        "textures": {
          "overlay": "gtceu:block/void",
          "overlay_emissive": "gtceu:block/void"
        }
      }
    },
    "active=false,hpca_part_damaged=false,is_formed=true": {
      "model": {
        "parent": "phoenixcore:block/phoenix_cooling_component_base",
        "textures": {
          "overlay": "gtceu:block/void",
          "overlay_emissive": "gtceu:block/void"
        }
      }
    },
    "active=false,hpca_part_damaged=true,is_formed=false": {
      "model": {
        "parent": "phoenixcore:block/phoenix_cooling_component_base",
        "textures": {
          "overlay": "gtceu:block/void",
          "overlay_emissive": "gtceu:block/void"
        }
      }
    },
    "active=false,hpca_part_damaged=true,is_formed=true": {
      "model": {
        "parent": "phoenixcore:block/phoenix_cooling_component_base",
        "textures": {
          "overlay": "gtceu:block/void",
          "overlay_emissive": "gtceu:block/void"
        }
      }
    },
    "active=true,hpca_part_damaged=false,is_formed=false": {
      "model": {
        "parent": "phoenixcore:block/phoenix_cooling_component_base",
        "textures": {
          "overlay": "gtceu:block/void",
          "overlay_emissive": "gtceu:block/void"
        }
      }
    },
    "active=true,hpca_part_damaged=false,is_formed=true": {
      "model": {
        "parent": "phoenixcore:block/phoenix_cooling_component_base",
        "textures": {
          "overlay": "gtceu:block/void",
          "overlay_emissive": "gtceu:block/void"
        }
      }
    },
    "active=true,hpca_part_damaged=true,is_formed=false": {
      "model": {
        "parent": "phoenixcore:block/phoenix_cooling_component_base",
        "textures": {
          "overlay": "gtceu:block/void",
          "overlay_emissive": "gtceu:block/void"
        }
      }
    },
    "active=true,hpca_part_damaged=true,is_formed=true": {
      "model": {
        "parent": "phoenixcore:block/phoenix_cooling_component_base",
        "textures": {
          "overlay": "gtceu:block/void",
          "overlay_emissive": "gtceu:block/void"
        }
      }
    }
  }
}